Metadata-Version: 2.1
Name: flops-compute
Version: 0.6.2
Summary: Flops counter for convolutional networks inpytorch framework
Home-page: UNKNOWN
Author: junxi
Author-email: 843525908@qq.com
License: MIT
Platform: UNKNOWN
Classifier: Programming Language :: Python :: 3
